pop_conf/conf/args.py
pop_conf/conf/dirs.py
pop_conf/conf/file_parser.py
pop_conf/conf/init.py
pop_conf/conf/integrate.py
pop_conf/conf/json_conf.py
pop_conf/conf/nix_os.py
pop_conf/conf/reader.py
pop_conf/conf/toml_conf.py
pop_conf/conf/version.py
pop_conf/conf/yaml_conf.py
pop_conf/conf/log/basic.py
pop_conf/conf/log/init.py
pop_conf/conf/recursive_contract/init.py
pop_conf-1.0.0.dist-info/LICENSE
pop_conf-1.0.0.dist-info/METADATA
pop_conf-1.0.0.dist-info/WHEEL
pop_conf-1.0.0.dist-info/entry_points.txt
pop_conf-1.0.0.dist-info/top_level.txt
pop_conf-1.0.0.dist-info/RECORD
