Metadata-Version: 2.1
Name: pop-conf
Version: 1.0.0
Summary: Legacy config module for pop
Home-page: https://www.saltstack.com
Author: Thomas S Hatch
Author-email: thatch45@gmail.com
License: UNKNOWN
Platform: UNKNOWN
Classifier: Operating System :: OS Independent
Classifier: Programming Language :: Python
Classifier: Programming Language :: Python :: 3.6
Classifier: Programming Language :: Python :: 3.7
Classifier: Programming Language :: Python :: 3.8
Classifier: Development Status :: 5 - Production/Stable
Requires-Python: >=3.6
Requires-Dist: pop
Requires-Dist: PyYAML
